{
  "resourceType" : "ValueSet",
  "id" : "OrganizationType",
  "text" : {
    "status" : "generated",
    "div" : "<div xmlns=\"http://www.w3.org/1999/xhtml\">Placeholder</div>"
  },
  "url" : "http://fhir.ch/ig/ch-ig/ValueSet/OrganizationType",
  "version" : "0.1.0",
  "name" : "OrganizationType",
  "title" : "Organization Type",
  "status" : "draft",
  "experimental" : true,
  "date" : "2023-09-05T12:08:22+00:00",
  "publisher" : "HL7 Switzerland",
  "contact" : [{
    "name" : "HL7 Switzerland",
    "telecom" : [{
      "system" : "url",
      "value" : "https://www.hl7.ch/"
    }]
  }],
  "description" : "Test value set",
  "jurisdiction" : [{
    "coding" : [{
      "system" : "urn:iso:std:iso:3166",
      "code" : "CHE"
    }]
  }],
  "copyright" : "CC0-1.0",
  "compose" : {
    "include" : [{
      "system" : "http://snomed.info/sct",
      "version" : "http://snomed.info/sct/2011000195101",
      "concept" : [{
        "code" : "288565001",
        "display" : "Medical center (environment)"
      },
      {
        "code" : "264372000",
        "display" : "Pharmacy (environment)"
      }]
    }]
  }
}