{
  "resourceType" : "OperationOutcome",
  "issue" : [{
    "severity" : "error",
    "code" : "business-rule",
    "details" : {
      "text" : "When HL7 is publishing a resource, the owning committee must be stated using the http://hl7.org/fhir/StructureDefinition/structuredefinition-wg extension"
    },
    "diagnostics" : "[1,2]",
    "expression" : ["CodeSystem"]
  },
  {
    "severity" : "information",
    "code" : "business-rule",
    "details" : {
      "text" : "Most code systems defined in HL7 IGs will need to move to THO later during the process. Consider giving this code system a THO URL now (See https://confluence.hl7.org/display/TSMG/Terminology+Play+Book, and/or talk to TSMG)"
    },
    "diagnostics" : "[1,2]",
    "expression" : ["CodeSystem"]
  }]
}