{
  "resourceType" : "OperationOutcome",
  "issue" : [{
    "severity" : "warning",
    "code" : "code-invalid",
    "details" : {
      "text" : "None of the codings provided are in the value set 'IdentifierType' (http://hl7.org/fhir/ValueSet/identifier-type|4.0.1), and a coding should come from this value set unless it has no suitable code (note that the validator cannot judge what is suitable) (codes = http://terminology.hl7.org/CodeSystem/v2-0203#NPI)"
    },
    "diagnostics" : "[89,10]",
    "expression" : ["Bundle.signature.who.identifier.type"]
  },
  {
    "severity" : "information",
    "code" : "informational",
    "details" : {
      "text" : "Signature Verification is a work in progress. Feedback welcome at https://chat.fhir.org/#narrow/channel/179247-Security-and-Privacy/topic/Signature/with/524324965"
    },
    "diagnostics" : "[1,2]",
    "expression" : ["Bundle"]
  },
  {
    "severity" : "warning",
    "code" : "value",
    "details" : {
      "text" : "The signature has a payload, but the signature should be a detached signature with no payload"
    },
    "diagnostics" : "[1,2]",
    "expression" : ["Bundle"]
  },
  {
    "severity" : "information",
    "code" : "informational",
    "details" : {
      "text" : "The signature verified OK"
    },
    "diagnostics" : "[1,2]",
    "expression" : ["Bundle"]
  },
  {
    "severity" : "information",
    "code" : "informational",
    "details" : {
      "text" : "The content was signed by 1.2.840.113549.1.9.1=#16146a68616e636f636b406578616d706c652e6f7267,CN=John Hancock\\, MD,O=Example Organization,L=Sausalito,ST=California,C=US (and this has been verified by the signature)"
    },
    "diagnostics" : "[1,2]",
    "expression" : ["Bundle"]
  },
  {
    "severity" : "information",
    "code" : "informational",
    "details" : {
      "text" : "The content claims to have been signed at 2020-10-23T04:54:56.048+00:00, but this has not been verified"
    },
    "diagnostics" : "[1,2]",
    "expression" : ["Bundle"]
  }]
}