{
  "resourceType" : "OperationOutcome",
  "issue" : [{
    "extension" : [{
      "url" : "http://hl7.org/fhir/StructureDefinition/operationoutcome-message-context",
      "valueString" : "https://fhir.kbv.de/StructureDefinition/Patient|0.0.0"
    }],
    "severity" : "error",
    "code" : "invariant",
    "details" : {
      "text" : "Constraint failed: pat-de-kbv-1: 'Test, ob auf den Straßennamen in der erster Adresszeile zugegriffen werden kann.' (defined in https://fhir.kbv.de/StructureDefinition/Patient)"
    },
    "diagnostics" : "[1,38]",
    "expression" : ["Patient"]
  }]
}